Workbook

Sheet Read me
A1: Institute Intelligence — 3-year financial model
A2: Case B · The Data Moat · Nextute × Finance Club IIT Patna 2026
A4: Purpose | B4: Bottom-up operating model for a Tier-2/3 coaching analytics pilot. Built for assumptions testing, not a forecast.
A5: Currency | B5: Indian rupees (INR), nominal. Fiscal year = April–March.
A6: Pricing | B6: ₹35/student/month (Starter) and ₹55/student/month (Growth); 10 billed months; 150-student floor.
A7: Revenue | B7: Recognised revenue uses average institutes in year × blended ACV. ARR uses year-end institutes.
A8: Costs | B8: Service cost includes cloud, support, onboarding amortisation, WhatsApp/SMS, payments and content ops.
A9: Fixed costs | B9: Team, office, tools, compliance and demand generation. Founder salaries below market in Year 1.
A10: Caveat | B10: All demand, churn and pricing assumptions are hypotheses to test with 10 design-partner institutes.
A11: Sheets | B11: Assumptions → Unit economics → 3-Year P&L → Break-even → Sensitivity → Use of funds.

Sheet Assumptions
A1: Assumptions
A2: Edit blue cells; downstream sheets recalculate.
A4: Driver | B4: Starter | C4: Growth | D4: Blended Y1 | E4: Notes
A5: Price per student per month (₹) | B5: 35 | C5: 55 | E5: Willingness-to-pay hypothesis
A6: Billed months per year | B6: 10 | C6: 10 | E6: April–January; Feb–Mar free
A7: Average students per institute | B7: 200 | C7: 350 | E7: Growth tier assumes 350
A8: Annual contract value (₹) | B8: =B5*B6*B7 | C8: =C5*C6*C7 | E8: Price × months × students
A9: Service cost per institute / year (₹) | B9: 25000 | C9: 66730 | E9: Cloud, support, onboarding, messaging
A10: Contribution per institute / year (₹) | B10: =B8-B9 | C10: =C8-C9 | E10: ACV minus service cost
A11: Contribution margin | B11: =B10/B8 | C11: =C10/C8 | E11: Gross margin before fixed costs
A14: Mix & scale | B14: Year 1 | C14: Year 2 | D14: Year 3 | E14: Notes
A15: Starter share of institutes | B15: 0.75 | C15: 0.7 | D15: 0.65 | E15: Land small, expand
A16: Growth share of institutes | B16: =1-B15 | C16: =1-C15 | D16: =1-D15 | E16: Residual
A17: Blended ACV (₹) | B17: =B15*$B$8+C15*$C$8 | C17: =C15*$B$8+D15*$C$8 | D17: =D15*$B$8+E15*$C$8
A18: Blended contribution (₹) | B18: =B15*$B$10+C15*$C$10 | C18: =C15*$B$10+D15*$C$10 | D18: =D15*$B$10+E15*$C$10
A19: Year-end institutes | B19: 40 | C19: 140 | D19: 320 | E19: Sales capacity ramp
A20: Average institutes in year | B20: 18 | C20: 88 | D20: 225 | E20: Lag between adds and revenue
A21: Year-end students | B21: =B19*(B15*$B$7+C15*$C$7) | C21: =C19*(C15*$B$7+D15*$C$7) | D21: =D19*(D15*$B$7+E15*$C$7)
A23: Fixed cost base | B23: Year 1 | C23: Year 2 | D23: Year 3 | E23: Notes
A24: Team (₹) | B24: 4800000 | C24: 6000000 | D24: 7800000 | E24: 5–9 people; below-market founder pay
A25: Demand generation (₹) | B25: 800000 | C25: 1200000 | D25: 1800000 | E25: Founder-led + referrals
A26: Office, tools, cloud (₹) | B26: 900000 | C26: 1100000 | D26: 1400000 | E26: Lean Patna office
A27: Compliance, legal, audit (₹) | B27: 400000 | C27: 500000 | D27: 700000 | E27: DPDP, contracts, security
A28: Content & assessment ops (₹) | B28: 700000 | C28: 400000 | D28: 300000 | E28: Curated library, item review
A29: Total fixed cost (₹) | B29: =SUM(B24:B28) | C29: =SUM(C24:C28) | D29: =SUM(D24:D28)

Sheet Unit economics
A1: Unit economics
A2: One institute, first 12 months.
A4: Metric | B4: Starter | C4: Growth
A5: ACV (₹) | B5: =Assumptions!B8 | C5: =Assumptions!C8
A6: Service cost (₹) | B6: =Assumptions!B9 | C6: =Assumptions!C9
A7: Contribution (₹) | B7: =B5-B6 | C7: =C5-C6
A8: Contribution margin | B8: =B7/B5 | C8: =C7/C5
A9: CAC (₹) | B9: 38000 | C9: 38000
A10: CAC payback (months) | B10: =B9/(B7/12) | C10: =C9/(C7/12)
A11: Average life (months) | B11: 30 | C11: 30
A12: LTV (₹) | B12: =B7/12*B11 | C12: =C7/12*C11
A13: LTV / CAC | B13: =B12/B9 | C13: =C12/C9

Sheet 3-Year P&L
A1: 3-year P&L
A2: Revenue recognition uses average institutes; ARR uses year-end.
A4: Line item (₹) | B4: Year 1 | C4: Year 2 | D4: Year 3
A5: Starter share | B5: =Assumptions!B15 | C5: =Assumptions!C15 | D5: =Assumptions!D15
A6: Growth share | B6: =Assumptions!B16 | C6: =Assumptions!C16 | D6: =Assumptions!D16
A7: Blended ACV | B7: =Assumptions!B17 | C7: =Assumptions!C17 | D7: =Assumptions!D17
A8: Average institutes | B8: =Assumptions!B20 | C8: =Assumptions!C20 | D8: =Assumptions!D20
A9: Revenue | B9: =B8*B7 | C9: =C8*C7 | D9: =D8*D7
A10: Blended contribution per institute | B10: =Assumptions!B18 | C10: =Assumptions!C18 | D10: =Assumptions!D18
A11: Contribution | B11: =B8*B10 | C11: =C8*C10 | D11: =D8*D10
A12: Service cost | B12: =B9-B11 | C12: =C9-C11 | D12: =D9-D11
A13: Fixed cost | B13: =Assumptions!B29 | C13: =Assumptions!C29 | D13: =Assumptions!D29
A14: EBITDA | B14: =B11-B13 | C14: =C11-C13 | D14: =D11-D13
A15: EBITDA margin | B15: =B14/B9 | C15: =C14/C9 | D15: =D14/D9
A16: Cumulative EBITDA | B16: =B14 | C16: =B16+C14 | D16: =C16+D14
A17: Year-end institutes | B17: =Assumptions!B19 | C17: =Assumptions!C19 | D17: =Assumptions!D19
A18: Year-end students | B18: =Assumptions!B21 | C18: =Assumptions!C21 | D18: =Assumptions!D21
A19: ARR (year-end institutes × ACV) | B19: =B17*B7 | C19: =C17*C7 | D19: =D17*D7

Sheet Break-even
A1: Break-even and funding
A2: Break-even at the Year-1 fixed cost base.
A5: Year-1 fixed cost (₹) | B5: =Assumptions!B29
A6: Blended contribution per institute (Year 2 mix) (₹) | B6: =Assumptions!C18
A7: Break-even institutes | B7: =B5/B6
A8: Growth-tier contribution / month (₹) | B8: =Assumptions!C10/12
A9: Growth-tier CAC payback (months) | B9: =38000/B8
A10: Peak cumulative EBITDA (₹) | B10: ='3-Year P&L'!C16
A11: Funding ask (₹) | B11: 10000000
A12: Runway / buffer (₹) | B12: =B11+B10

Sheet Sensitivity
A1: Sensitivity
A2: Year-3 EBITDA (₹ lakh) vs average institutes and fixed cost.
A4: Average institutes → | B4: 180 | C4: 225 | D4: 270
A5: 10800000 | B5: =(180*Assumptions!D18-10800000)/100000 | C5: =(225*Assumptions!D18-10800000)/100000 | D5: =(270*Assumptions!D18-10800000)/100000
A6: 12000000 | B6: =(180*Assumptions!D18-12000000)/100000 | C6: =(225*Assumptions!D18-12000000)/100000 | D6: =(270*Assumptions!D18-12000000)/100000
A7: 13200000 | B7: =(180*Assumptions!D18-13200000)/100000 | C7: =(225*Assumptions!D18-13200000)/100000 | D7: =(270*Assumptions!D18-13200000)/100000

Sheet Use of funds
A1: Use of funds — ₹1.0 crore
A2: 18-month plan to 110+ paying institutes.
A4: Category | B4: Amount (₹) | C4: Share | D4: What it buys
A5: Product & engineering | B5: 3500000 | C5: =B5/10000000 | D5: Two engineers; import/analytics/report hardening, OMR adapter.
A6: Pilot delivery & onboarding | B6: 2000000 | C6: =B6/10000000 | D6: 10 design partners; data cleaning; teacher training.
A7: Sales & channel | B7: 2000000 | C7: =B7/10000000 | D7: Founder-led sales, local events, referral incentives.
A8: Content & assessment ops | B8: 1000000 | C8: =B8/10000000 | D8: Curated topic briefs, item review, Hindi QA.
A9: Compliance, legal, security | B9: 500000 | C9: =B9/10000000 | D9: DPDP notices, DPA, audit, penetration test.
A10: Working capital & buffer | B10: 1000000 | C10: =B10/10000000 | D10: Receivables, contingency.
A11: Total | B11: =SUM(B5:B10) | C11: =SUM(C5:C10)
